cowhatif/__init__.py
cowhatif-0.0.0.dist-info/LICENSE
cowhatif-0.0.0.dist-info/METADATA
cowhatif-0.0.0.dist-info/WHEEL
cowhatif-0.0.0.dist-info/top_level.txt
cowhatif-0.0.0.dist-info/RECORD
